mcross/__init__.py
mcross/conf.py
mcross/document.py
mcross/gui/__init__.py
mcross/gui/controller.py
mcross/gui/model.py
mcross/gui/view.py
mcross/gui/widgets.py
mcross/transport.py
mcross-0.5.19.dist-info/entry_points.txt
mcross-0.5.19.dist-info/LICENSE
mcross-0.5.19.dist-info/WHEEL
mcross-0.5.19.dist-info/METADATA
mcross-0.5.19.dist-info/RECORD
