Metadata-Version: 2.1
Name: mcross
Version: 0.5.19
Summary: Do you remember www?
Home-page: https://sr.ht/~nhanb/mcross/
License: AGPL-3.0-only
Author: nhanb
Author-email: hi@imnhan.com
Requires-Python: >=3.7,<4.0
Classifier: License :: OSI Approved :: GNU Affero General Public License v3
Classifier: Programming Language :: Python :: 3
Classifier: Programming Language :: Python :: 3.7
Classifier: Programming Language :: Python :: 3.8
Requires-Dist: appdirs (>=1.4.4,<2.0.0)
Requires-Dist: curio (>=1.2,<2.0)
Requires-Dist: toml (>=0.10.1,<0.11.0)
Project-URL: Repository, https://git.sr.ht/~nhanb/mcross
